flake8_commas/__init__.py
flake8_trailing_commas-0.1.3.dist-info/DESCRIPTION.rst
flake8_trailing_commas-0.1.3.dist-info/METADATA
flake8_trailing_commas-0.1.3.dist-info/RECORD
flake8_trailing_commas-0.1.3.dist-info/WHEEL
flake8_trailing_commas-0.1.3.dist-info/entry_points.txt
flake8_trailing_commas-0.1.3.dist-info/metadata.json
flake8_trailing_commas-0.1.3.dist-info/top_level.txt
